{
    "predictions": [
        {
            "class": "0",
            "score": "81.17731809616089",
            "box": {
                "x1": "1823",
                "y1": "287",
                "x2": "1921",
                "y2": "401"
            }
        },
        {
            "class": "0",
            "score": "79.56956624984741",
            "box": {
                "x1": "1729",
                "y1": "404",
                "x2": "1837",
                "y2": "532"
            }
        },
        {
            "class": "0",
            "score": "72.26369380950928",
            "box": {
                "x1": "652",
                "y1": "436",
                "x2": "717",
                "y2": "541"
            }
        },
        {
            "class": "0",
            "score": "68.34811568260193",
            "box": {
                "x1": "1054",
                "y1": "347",
                "x2": "1121",
                "y2": "454"
            }
        }
    ],
    "time": "2024-07-08T18:54:39.4640000+05:30"
}